{
  "id": "troll-2",
  "symbol": "troll",
  "name": "TROLL",
  "web_slug": "troll-2",
  "asset_platform_id": "solana",
  "platforms": {
    "solana": "5UUH9RTDiSpq6HKS6bp4NdU9PNJpXRXuiw6ShBTBhgH2"
  },
  "detail_platforms": {
    "solana": {
      "decimal_place": 6,
      "contract_address": "5UUH9RTDiSpq6HKS6bp4NdU9PNJpXRXuiw6ShBTBhgH2",
      "geckoterminal_url": "https://www.geckoterminal.com/solana/tokens/5UUH9RTDiSpq6HKS6bp4NdU9PNJpXRXuiw6ShBTBhgH2"
    }
  },
  "block_time_in_minutes": 0,
  "hashing_algorithm": null,
  "categories": [
    "Solana Ecosystem",
    "Meme",
    "Solana Meme",
    "Parody Meme",
    "Pump.fun Ecosystem",
    "Binance Alpha Spotlight",
    "4chan-Themed",
    "IP Meme"
  ],
  "preview_listing": false,
  "public_notice": null,
  "additional_notices": [],
  "description": {
    "en": "The TROLL token on the Solana network is a meme coin inspired by internet trolling culture, designed for entertainment and community engagement with no intrinsic value. Built on Solana’s blockchain, it leverages the network’s fast transactions and low fees to appeal to meme enthusiasts. Launched on decentralized exchanges, TROLL aims to foster a fun, community-driven ecosystem through social media, influencer partnerships, and viral marketing, embodying the playful spirit of online trolling."
  },
  "links": {
    "homepage": [
      "https://trololol.io"
    ],
    "whitepaper": "",
    "blockchain_site": [
      "https://solscan.io/token/5UUH9RTDiSpq6HKS6bp4NdU9PNJpXRXuiw6ShBTBhgH2",
      "https://intel.arkm.com/explorer/token/troll-2"
    ],
    "official_forum_url": [
      "https://www.instagram.com/trololol_io"
    ],
    "chat_url": [],
    "announcement_url": [],
    "snapshot_url": null,
    "twitter_screen_name": "trololol_io",
    "facebook_username": "",
    "bitcointalk_thread_identifier": null,
    "telegram_channel_identifier": "trollsolog",
    "subreddit_url": null,
    "repos_url": {
      "github": [],
      "bitbucket": []
    }
  },
  "image": {
    "thumb": "https://coin-images.coingecko.com/coins/images/55282/thumb/trolllogo.png?1745215015",
    "small": "https://coin-images.coingecko.com/coins/images/55282/small/trolllogo.png?1745215015",
    "large": "https://coin-images.coingecko.com/coins/images/55282/large/trolllogo.png?1745215015"
  },
  "country_origin": "",
  "genesis_date": null,
  "contract_address": "5UUH9RTDiSpq6HKS6bp4NdU9PNJpXRXuiw6ShBTBhgH2",
  "sentiment_votes_up_percentage": 75.0,
  "sentiment_votes_down_percentage": 25.0,
  "watchlist_portfolio_users": 5383,
  "market_cap_rank": 765,
  "status_updates": [],
  "last_updated": "2026-01-05T02:27:58.661Z"
}